LICENSE
MANIFEST.in
README.md
setup.py
djcommerce/__init__.py
djcommerce/admin.py
djcommerce/apps.py
djcommerce/tests.py
djcommerce/utils.py
djcommerce.egg-info/PKG-INFO
djcommerce.egg-info/SOURCES.txt
djcommerce.egg-info/dependency_links.txt
djcommerce.egg-info/top_level.txt
djcommerce/models/__init__.py
djcommerce/models/address.py
djcommerce/models/cart.py
djcommerce/models/category.py
djcommerce/models/configuration.py
djcommerce/models/order.py
djcommerce/models/product.py
djcommerce/models/profile.py
djcommerce/models/__pycache__/__init__.cpython-37.pyc
djcommerce/models/__pycache__/address.cpython-37.pyc
djcommerce/models/__pycache__/cart.cpython-37.pyc
djcommerce/models/__pycache__/category.cpython-37.pyc
djcommerce/models/__pycache__/configuration.cpython-37.pyc
djcommerce/models/__pycache__/order.cpython-37.pyc
djcommerce/models/__pycache__/product.cpython-37.pyc
djcommerce/models/__pycache__/profile.cpython-37.pyc